{
    "final_data": [
        0,
        0,
        0,
        0,
        0,
        0,
        0,
        0,
        0,
        73,
        0,
        0,
        0,
        0,
        0,
        0,
        0,
        0,
        0,
        0,
        0,
        0,
        0,
        0,
        0,
        0,
        0,
        0,
        0,
        136,
        0,
        0,
        0,
        0,
        0,
        0,
        0,
        0,
        0,
        0,
        0,
        0,
        0,
        0,
        199,
        0,
        0,
        0,
        0,
        0,
        0,
        31,
        0,
        0,
        0,
        0,
        0,
        0,
        0,
        0,
        0,
        111,
        0,
        0,
        0,
        0,
        0,
        0,
        0,
        0,
        0,
        0,
        0,
        0,
        0,
        0,
        137,
        0,
        0,
        0,
        0,
        0,
        0,
        0,
        0,
        0,
        0,
        0,
        0,
        0,
        0,
        0,
        0,
        0,
        0,
        0,
        114,
        199,
        0,
        0
    ],
    "initial_amount": 10,
    "m_duration": 1000,
    "m_type": "cant_trade",
    "num_people": 100
}
